{
  "articles": [
    {
      "id": "1",
      "source": {
        "id": "bloomberg",
        "name": "Bloomberg"
      },
      "author": null,
      "title": "BOEING Gets Obama Pep Talk After $10M Library Donation...",
      "description": "BOEING Gets Obama Pep Talk After $10M Library Donation... (Third column, 12th story, link ) Advertise here",
      "url": "https://www.bloomberg.com/tosv2.html?vid=&uuid=b58e6370-2334-11e9-8978-c733aaefb995&url=L25ld3MvYXJ0aWNsZXMvMjAxOS0wMS0yOC9ib2VpbmctZ2V0cy1vYmFtYS1wZXAtdGFsay1hZnRlci1naXZpbmctbWlsbGlvbnMtdG8tbGlicmFyeS1mdW5k",
      "urlToImage": null,
      "publishedAt": "2019-01-28T19:28:38Z",
      "content": null
    },
    {
      "id": "3",
      "source": {
        "id": "bloomberg",
        "name": "Bloomberg"
      },
      "author": null,
      "title": "Roger Stone: A Question Mark in Mueller Probe (Podcast)",
      "description": null,
      "url": "https://www.bloomberg.com/tosv2.html?vid=&uuid=826b6a60-2334-11e9-a2a3-370ca824fc91&url=L25ld3MvYXVkaW8vMjAxOS0wMS0yOC9yb2dlci1zdG9uZS1hLXF1ZXN0aW9uLW1hcmstaW4tbXVlbGxlci1wcm9iZS1wb2RjYXN0LWpyZ29zcmIy",
      "urlToImage": null,
      "publishedAt": "2019-01-28T18:49:11Z",
      "content": null
    },
    {
      "id": "4",
      "source": {
        "id": "bloomberg",
        "name": "Bloomberg"
      },
      "author": null,
      "title": "Saudi Oil Production Will Be 'Well Below' Cap, Energy Min. Says",
      "description": null,
      "url": "https://www.bloomberg.com/tosv2.html?vid=&uuid=53ef8800-2330-11e9-a85d-c56f1c17ead4&url=L25ld3MvdmlkZW9zLzIwMTktMDEtMjgvc2F1ZGktb2lsLXByb2R1Y3Rpb24td2lsbC1iZS13ZWxsLWJlbG93LWNhcC1lbmVyZ3ktbWluLXNheXMtdmlkZW8=",
      "urlToImage": null,
      "publishedAt": "2019-01-28T18:46:20Z",
      "content": null
    },
    {
      "id": "5",
      "source": {
        "id": "bloomberg",
        "name": "Bloomberg"
      },
      "author": null,
      "title": "It's a Big Week for Funds That Are Ready to Buy $45 Billion of Stocks",
      "description": null,
      "url": "https://www.bloomberg.com/tosv2.html?vid=&uuid=88188290-2334-11e9-a55d-a5eb5c4fff85&url=L25ld3MvYXJ0aWNsZXMvMjAxOS0wMS0yOC9pdC1zLWEtYmlnLXdlZWstZm9yLWZ1bmRzLWdpcmRpbmctdG8tYnV5LTQ1LWJpbGxpb24tb2Ytc3RvY2tz",
      "urlToImage": null,
      "publishedAt": "2019-01-28T18:40:31Z",
      "content": null
    },
    {
      "id": "6",
      "source": {
        "id": "bloomberg",
        "name": "Bloomberg"
      },
      "author": null,
      "title": "'Bloomberg Markets: The Open' Full Show (01/28/2019)",
      "description": null,
      "url": "https://www.bloomberg.com/tosv2.html?vid=&uuid=49f854f0-232e-11e9-9d70-2b5b1f639e97&url=L25ld3MvdmlkZW9zLzIwMTktMDEtMjgvLWJsb29tYmVyZy1tYXJrZXRzLXRoZS1vcGVuLWZ1bGwtc2hvdy0wMS0yOC0yMDE5LXZpZGVv",
      "urlToImage": null,
      "publishedAt": "2019-01-28T18:34:10Z",
      "content": null
    },
    {
      "id": "7",
      "source": {
        "id": "bloomberg",
        "name": "Bloomberg"
      },
      "author": null,
      "title": "Boeing Gets Obama Pep Talk After Giving Millions to Library Fund",
      "description": null,
      "url": "https://www.bloomberg.com/tosv2.html?vid=&uuid=51bffdd0-2330-11e9-a113-5b306adecac6&url=L25ld3MvYXJ0aWNsZXMvMjAxOS0wMS0yOC9ib2VpbmctZ2V0cy1vYmFtYS1wZXAtdGFsay1hZnRlci1naXZpbmctbWlsbGlvbnMtdG8tbGlicmFyeS1mdW5k",
      "urlToImage": null,
      "publishedAt": "2019-01-28T18:33:47Z",
      "content": null
    },
    {
      "id": "8",
      "source": {
        "id": "bloomberg",
        "name": "Bloomberg"
      },
      "author": null,
      "title": "Daybreak: Corporate America Blames China. Stocks Dip. (Podcast)",
      "description": null,
      "url": "https://www.bloomberg.com/tosv2.html?vid=&uuid=7d0b5d90-2330-11e9-beac-094084179037&url=L25ld3MvYXVkaW8vMjAxOS0wMS0yOC9kYXlicmVhay1jb3Jwb3JhdGUtYW1lcmljYS1ibGFtZXMtY2hpbmEtc3RvY2tzLWRpcC1wb2RjYXN0",
      "urlToImage": null,
      "publishedAt": "2019-01-28T18:32:54Z",
      "content": null
    },
    {
      "id": "9",
      "source": {
        "id": "bloomberg",
        "name": "Bloomberg"
      },
      "author": null,
      "title": "May Backs Plan to Scrap Brexit Backstop in Struggle for a Deal",
      "description": null,
      "url": "https://www.bloomberg.com/tosv2.html?vid=&uuid=73ac12d0-2330-11e9-9e01-ade2a774f620&url=L25ld3MvYXJ0aWNsZXMvMjAxOS0wMS0yOC9tYXktYmFja3MtcGxhbi10by1zY3JhcC1icmV4aXQtYmFja3N0b3AtaW4tc3RydWdnbGUtZm9yLWEtZGVhbA==",
      "urlToImage": null,
      "publishedAt": "2019-01-28T18:30:20Z",
      "content": null
    },
    {
      "id": "10",
      "source": {
        "id": "bloomberg",
        "name": "Bloomberg"
      },
      "author": null,
      "title": "Ocasio-Cortez Slams Tech Giants Over Climate Denial at Conference",
      "description": null,
      "url": "https://www.bloomberg.com/tosv2.html?vid=&uuid=6ae42610-2330-11e9-8aff-2df9aa7561f7&url=L25ld3MvYXJ0aWNsZXMvMjAxOS0wMS0yOC9vY2FzaW8tY29ydGV6LXNsYW1zLXRlY2gtZ2lhbnRzLW9uLWNsaW1hdGUtY2hhbmdlLWRlbmlhbC10YWxr",
      "urlToImage": null,
      "publishedAt": "2019-01-28T18:23:38Z",
      "content": null
    },
    {
      "id": "11",
      "source": {
        "id": "bloomberg",
        "name": "Bloomberg"
      },
      "author": null,
      "title": "U.S. Trade Barriers Will Hurt the Economy, CBO Says, Contradicting Trump",
      "description": null,
      "url": "https://www.bloomberg.com/tosv2.html?vid=&uuid=3d80a6a0-232e-11e9-86bf-f1c0450275eb&url=L25ld3MvYXJ0aWNsZXMvMjAxOS0wMS0yOC90cnVtcC1jb250cmFkaWN0ZWQtYnktY2JvLXNlZWluZy10cmFkZS13YXItZHJhZy1vbi11LXMtZWNvbm9teQ==",
      "urlToImage": null,
      "publishedAt": "2019-01-28T18:13:04Z",
      "content": null
    },
    {
      "id": "12",
      "source": {
        "id": "bloomberg",
        "name": "Bloomberg"
      },
      "author": null,
      "title": "Vestager Sticks Another Knife Into Macron's Plan for EU Revival",
      "description": null,
      "url": "https://www.bloomberg.com/tosv2.html?vid=&uuid=71880c40-232e-11e9-9f9d-71b22a7bdd07&url=L25ld3MvYXJ0aWNsZXMvMjAxOS0wMS0yOC92ZXN0YWdlci1zdGlja3MtYW5vdGhlci1rbmlmZS1pbnRvLW1hY3Jvbi1zLXBsYW4tZm9yLWV1LXJldml2YWw=",
      "urlToImage": null,
      "publishedAt": "2019-01-28T18:08:39Z",
      "content": null
    }
  ]
}